mcpydoc/__init__.py
mcpydoc/__main__.py
mcpydoc/analyzer.py
mcpydoc/documentation.py
mcpydoc/exceptions.py
mcpydoc/mcp_server.py
mcpydoc/models.py
mcpydoc/security.py
mcpydoc/server.py
mcpydoc/utils.py
mcpydoc-1.2.0.dist-info/METADATA
mcpydoc-1.2.0.dist-info/WHEEL
mcpydoc-1.2.0.dist-info/entry_points.txt
mcpydoc-1.2.0.dist-info/licenses/LICENSE
mcpydoc-1.2.0.dist-info/RECORD
