Metadata-Version: 2.4
Name: mcpydoc
Version: 1.2.0
Summary: Model Context Protocol (MCP) server providing documentation and code analysis for Python packages
Project-URL: Homepage, https://github.com/amit608/MCPyDoc
Project-URL: Repository, https://github.com/amit608/MCPyDoc
Project-URL: Issues, https://github.com/amit608/MCPyDoc/issues
Author: Amit Ronen
License-Expression: MIT
License-File: LICENSE
Keywords: ai-agent,api-documentation,cline,code-analysis,docstring-parsing,documentation,github-copilot,introspection,mcp,model-context-protocol,package-analysis,python-packages
Classifier: Development Status :: 5 - Production/Stable
Classifier: Environment :: Console
Classifier: Intended Audience :: Developers
Classifier: License :: OSI Approved :: MIT License
Classifier: Operating System :: OS Independent
Classifier: Programming Language :: Python :: 3
Classifier: Programming Language :: Python :: 3.9
Classifier: Programming Language :: Python :: 3.10
Classifier: Programming Language :: Python :: 3.11
Classifier: Programming Language :: Python :: 3.12
Classifier: Topic :: Internet :: WWW/HTTP :: HTTP Servers
Classifier: Topic :: Software Development :: Documentation
Classifier: Topic :: Software Development :: Libraries :: Python Modules
Classifier: Topic :: System :: Software Distribution
Classifier: Topic :: Text Processing :: Markup
Classifier: Typing :: Typed
Requires-Python: >=3.9
Requires-Dist: aiohttp>=3.8.0
Requires-Dist: docstring-parser>=0.15
Requires-Dist: importlib-metadata>=4.0.0
Requires-Dist: pydantic>=2.0.0
Requires-Dist: typing-extensions>=4.0.0
Provides-Extra: dev
Requires-Dist: black>=22.0.0; extra == 'dev'
Requires-Dist: build>=0.10.0; extra == 'dev'
Requires-Dist: isort>=5.0.0; extra == 'dev'
Requires-Dist: mypy>=1.0.0; extra == 'dev'
Requires-Dist: pytest-asyncio>=0.21.0; extra == 'dev'
Requires-Dist: pytest-cov>=4.0.0; extra == 'dev'
Requires-Dist: pytest>=7.0.0; extra == 'dev'
Requires-Dist: twine>=4.0.0; extra == 'dev'
